{
	"agency": "USDA",
	"organization":" ",
	"projects": [{
		"status": " ",
    "vcs": "git",
		"repository": "git://github.com/USDA/USDA-APIs.git",
		"name": "USDA-APIs",
		"repoID": "10064296",
		"homepage": "www.usda.gov/developer",
		"downloadURL": " ",
		"description": "Do you have feedback, ideas, or questions for USDA APIs? Use this repository's Issue Tracker to join the discussion. ",
		"contact": [{
			"email": " ",
			"name": " ",
			"twitter": " ",
			"phone": " "
		}],
		"partners": [{
			"name": " "
		}, {
			"email": " "
		}],
		"license": "https://path.to/license",
		"openproject": 1,
		"govwideReuseproject": 0,
		"closedproject": 0,
		"exemption": null,
		"projectTags": [{
			"tag": "feedback"
		}, {
			"tag": "ideas"
		}, {
			"tag": "questions"
		}, {
			"tag": "usda"
		}, {
			"tag": "apis"
		}, {
			"tag": "use"
		}, {
			"tag": "repository"
		}, {
			"tag": "s"
		}, {
			"tag": "issue"
		}, {
			"tag": "tracker"
		}, {
			"tag": "join"
		}, {
			"tag": "discussion"
		}, {
			"tag": ""
		}],
		"codeLanguage": []
	}, {
		"status": " ",
    "vcs": "git",
		"repository": "git://github.com/USDA/RIDB.git",
		"name": "RIDB",
		"repoID": "29924484",
		"homepage": "https://usda.github.io/RIDB",
		"downloadURL": " ",
		"description": "Recreation Information Database ",
		"contact": [{
			"email": " ",
			"name": " ",
			"twitter": " ",
			"phone": " "
		}],
		"partners": [{
			"name": " "
		}, {
			"email": " "
		}],
		"license": "https://path.to/license",
		"openproject": 1,
		"govwideReuseproject": 0,
		"closedproject": 0,
		"exemption": null,
		"projectTags": [{
			"tag": "recreation"
		}, {
			"tag": "information"
		}, {
			"tag": "database"
		}],
		"codeLanguage": [{
			"language": "HTML"
		}]
	}, {
		"status": " ",
    "vcs": "git",
		"repository": "git://github.com/USDA/data-standards.git",
		"name": "data-standards",
		"repoID": "64396310",
		"homepage": "https://usda.github.io/data-standards",
		"downloadURL": " ",
		"description": "A collaborative site for official USDA data elements and data standards. ",
		"contact": [{
			"email": " ",
			"name": " ",
			"twitter": " ",
			"phone": " "
		}],
		"partners": [{
			"name": " "
		}, {
			"email": " "
		}],
		"license": "https://path.to/license",
		"openproject": 1,
		"govwideReuseproject": 0,
		"closedproject": 0,
		"exemption": null,
		"projectTags": [{
			"tag": "collaborative"
		}, {
			"tag": "site"
		}, {
			"tag": "official"
		}, {
			"tag": "usda"
		}, {
			"tag": "data"
		}, {
			"tag": "elements"
		}, {
			"tag": "data"
		}, {
			"tag": "standards"
		}, {
			"tag": ""
		}],
		"codeLanguage": [{
			"language": "CSS"
		}]
	}]
}