{
  "agency": "DHHS",
  "organization": "Department of Health and Human Services",
  "projects": [
    {
      "name": "ckanext-datajson",
      "description": "Custom CKAN extension for HealthData.gov",
      "license": "http://creativecommons.org/publicdomain/zero/1.0/",
      "openSourceProject": 1,
      "governmentWideReuseProject": 1,
      "tags": [
        "ckan",
        "json",
        "open data"
      ],
      "contact": {
        "email": "ServiceDesk.OCIO.HHS@hhs.gov",
        "name": "Office of the Chief Information Officer"
      },
      "vcs": "git",
      "repository": "https://github.com/HHS/ckanext-datajson"
    },
    {
      "name": "ckanext-harvest",
      "description": "CKAN remote harvesting extension",
      "license": null,
      "openSourceProject": 1,
      "governmentWideReuseProject": 1,
      "tags": [
        "ckan",
        "harvest",
        "open data"
      ],
      "contact": {
        "email": "ServiceDesk.OCIO.HHS@hhs.gov",
        "name": "Office of the Chief Information Officer"
      },
      "vcs": "git",
      "repository": "https://github.com/HHS/ckanext-harvest"
    },
    {
      "name": "lodestar",
      "description": "Linked Data explorer and SPARQL endpoint",
      "license": "http://www.apache.org/licenses/LICENSE-2.0",
      "openSourceProject": 1,
      "governmentWideReuseProject": 1,
      "tags": [
        "linked data",
        "SPARQL",
        "open data"
      ],
      "contact": {
        "email": "ServiceDesk.OCIO.HHS@hhs.gov",
        "name": "Office of the Chief Information Officer"
      },
      "vcs": "git",
      "repository": "https://github.com/HHS/lodestar"
    },
    {
      "name": "Healthcare Fraud Prevention",
      "description": "Code from the Healthcare Fraud Prevention Partnership challenge",
      "license": "http://www.apache.org/licenses/LICENSE-2.0",
      "openSourceProject": 1,
      "governmentWideReuseProject": 1,
      "tags": [
        "healthcare",
        "fraud prevention"
      ],
      "contact": {
        "email": "ServiceDesk.OCIO.HHS@hhs.gov",
        "name": "Office of the Chief Information Officer"
      },
      "vcs": "git",
      "repository": "https://github.com/HHS/lodestar"
    },
    {
      "name": "FNMS",
      "description": "Foreign National Management System",
      "license": null,
      "openSourceProject": 0,
      "governmentWideReuseProject": 1,
      "tags": [
        "government",
        "foreign",
        "visitor",
        "people"
      ],
      "contact": {
        "email": "ServiceDesk.OCIO.HHS@hhs.gov",
        "name": "Office of the Chief Information Officer"
      },
      "status": "Alpha"
    },
    {
      "name": "ARAPS",
      "description": "Automated Reasonable Accomodation Processing System",
      "license": null,
      "openSourceProject": 0,
      "governmentWideReuseProject": 1,
      "tags": [
        "government",
        "accomodation",
        "people"
      ],
      "contact": {
        "email": "ServiceDesk.OCIO.HHS@hhs.gov",
        "name": "Office of the Chief Information Officer"
      },
      "status": "Alpha"
    },
    {
      "name": "MMS",
      "description": "Menotoring Matching System",
      "license": null,
      "openSourceProject": 0,
      "governmentWideReuseProject": 1,
      "tags": [
        "Mentoring",
        "HHSU"
      ],
      "contact": {
        "email": "ServiceDesk.OCIO.HHS@hhs.gov",
        "name": "Office of the Chief Information Officer"
      },
      "status": "Alpha"
    }
  ]
}
